binaryninja_mcp/__init__.py
binaryninja_mcp/cli.py
binaryninja_mcp/consts.py
binaryninja_mcp/log.py
binaryninja_mcp/plugin.py
binaryninja_mcp/resources.py
binaryninja_mcp/server.py
binaryninja_mcp/tools.py
binaryninja_mcp/utils.py
binaryninja_mcp-0.3.1.dist-info/METADATA
binaryninja_mcp-0.3.1.dist-info/WHEEL
binaryninja_mcp-0.3.1.dist-info/entry_points.txt
binaryninja_mcp-0.3.1.dist-info/licenses/LICENSE
binaryninja_mcp-0.3.1.dist-info/RECORD
