Metadata-Version: 2.4
Name: binaryninja-mcp
Version: 0.3.1
Summary: The MCP server plugin for Binary Ninja, enables LLM integration by Model Context Protocol (MCP) through SSE or STDIO transport.
Author-email: ttimasdf <opensource@rabit.pw>
License: Apache 2.0
License-File: LICENSE
Keywords: automation,binaryninja,client,gpt,llm,mcp,plugin,server
Classifier: Development Status :: 4 - Beta
Classifier: Intended Audience :: Developers
Classifier: Intended Audience :: End Users/Desktop
Classifier: Intended Audience :: Information Technology
Classifier: License :: OSI Approved :: Apache Software License
Classifier: Operating System :: Microsoft :: Windows
Classifier: Operating System :: POSIX :: Linux
Classifier: Programming Language :: Python :: 3
Classifier: Programming Language :: Python :: 3.10
Classifier: Programming Language :: Python :: 3.11
Classifier: Programming Language :: Python :: 3.12
Classifier: Programming Language :: Python :: 3.13
Requires-Python: >=3.10
Requires-Dist: anyio>=4.9.0
Requires-Dist: hypercorn>=0.17.3
Requires-Dist: mcp>=1.6.0
Requires-Dist: trio>=0.29.0
